websockets/__init__.py
websockets/__main__.py
websockets/auth.py
websockets/client.py
websockets/connection.py
websockets/datastructures.py
websockets/exceptions.py
websockets/frames.py
websockets/headers.py
websockets/http.py
websockets/http11.py
websockets/imports.py
websockets/protocol.py
websockets/py.typed
websockets/server.py
websockets/streams.py
websockets/typing.py
websockets/uri.py
websockets/utils.py
websockets/version.py
websockets/extensions/__init__.py
websockets/extensions/base.py
websockets/extensions/permessage_deflate.py
websockets/legacy/__init__.py
websockets/legacy/async_timeout.py
websockets/legacy/auth.py
websockets/legacy/client.py
websockets/legacy/compatibility.py
websockets/legacy/framing.py
websockets/legacy/handshake.py
websockets/legacy/http.py
websockets/legacy/protocol.py
websockets/legacy/server.py
websockets/sync/__init__.py
websockets/sync/client.py
websockets/sync/compatibility.py
websockets/sync/connection.py
websockets/sync/messages.py
websockets/sync/server.py
websockets/sync/utils.py
websockets-11.0.dist-info/LICENSE
websockets-11.0.dist-info/METADATA
websockets-11.0.dist-info/WHEEL
websockets-11.0.dist-info/top_level.txt
websockets-11.0.dist-info/RECORD
