Metadata-Version: 2.1
Name: websockets
Version: 11.0
Summary: An implementation of the WebSocket Protocol (RFC 6455 & 7692)
Author-email: Aymeric Augustin <aymeric.augustin@m4x.org>
License: BSD-3-Clause
Project-URL: homepage, https://github.com/aaugustin/websockets
Project-URL: changelog, https://websockets.readthedocs.io/en/stable/project/changelog.html
Project-URL: documentation, https://websockets.readthedocs.io/
Project-URL: funding, https://tidelift.com/subscription/pkg/pypi-websockets?utm_source=pypi-websockets&utm_medium=referral&utm_campaign=readme
Project-URL: tracker, https://github.com/aaugustin/websockets/issues
Keywords: WebSocket
Classifier: Development Status :: 5 - Production/Stable
Classifier: Environment :: Web Environment
Classifier: Intended Audience :: Developers
Classifier: License :: OSI Approved :: BSD License
Classifier: Operating System :: OS Independent
Classifier: Programming Language :: Python
Classifier: Programming Language :: Python :: 3
Classifier: Programming Language :: Python :: 3.7
Classifier: Programming Language :: Python :: 3.8
Classifier: Programming Language :: Python :: 3.9
Classifier: Programming Language :: Python :: 3.10
Classifier: Programming Language :: Python :: 3.11
Requires-Python: >=3.7
License-File: LICENSE
